pystorge/__init__.py
pystorge/favicon.ico
storge-1.26.data/scripts/storge
storge-1.26.data/scripts/storged
storge-1.26.data/scripts/torge
storge-1.26.dist-info/LICENSE.txt
storge-1.26.dist-info/METADATA
storge-1.26.dist-info/WHEEL
storge-1.26.dist-info/top_level.txt
storge-1.26.dist-info/RECORD
