Metadata-Version: 2.2
Name: storge
Version: 1.26
Summary: Web file storage
Home-page: https://codeberg.org/gwync/storge
Author: Gwyn Ciesla
Author-email: gwync@protonmail.com
License: GPLv3+
Classifier: Programming Language :: Python :: 3
Classifier: License :: OSI Approved :: GNU General Public License v3 or later (GPLv3+)
Classifier: Operating System :: OS Independent
Requires-Python: >=3.8
License-File: LICENSE.txt
Requires-Dist: requests
Requires-Dist: cherrypy
Requires-Dist: pyOpenSSL
Requires-Dist: sqlalchemy
Requires-Dist: pymysql
Requires-Dist: psutil
